syntetica_sdk/__init__.py
syntetica_sdk/core.py
syntetica_sdk/dataset.py
syntetica_sdk/dataset_config.py
syntetica_sdk/exception.py
syntetica_sdk/rules.py
syntetica_sdk/utils.py
syntetica_sdk-1.0.0.dist-info/licenses/LICENSE
syntetica_sdk-1.0.0.dist-info/METADATA
syntetica_sdk-1.0.0.dist-info/WHEEL
syntetica_sdk-1.0.0.dist-info/top_level.txt
syntetica_sdk-1.0.0.dist-info/RECORD
